{"name": "\u56db\u4e2a\u6708\u4eae", "url": "https://movie.douban.com/subject/25767853", "writer": ["Sergio Tovar Velarde"], "actor": ["\u5b89\u4e1c\u5c3c\u5965\u00b7\u8d1d\u62c9\u5179\u594e\u65af", "Alejandro de la Madrid", "\u51ef\u6492\u00b7\u62c9\u83ab\u65af", "Gustavo Egelhaaf", "Alonso Ech\u00e1nove", "Alejandro Belmonte", "Gabriel Santoyo", "Sebasti\u00e1n Rivera", "M\u00f3nica Dionne", "Marta Aura", "Hugo Catal\u00e1n", "Jorge Luis Moreno", "Karina Gidi", "Juan Manuel Bernal", "Diego Alfonso"], "summary": "\u53d1\u751f\u5728\u58a8\u897f\u54e5\u3001\u5173\u4e8e\u7231\u548c\u8ba4\u540c\u7684\u56db\u4e2a\u6545\u4e8b\uff1a11\u5c81\u7684\u5c0f\u7537\u5b69\u60f3\u8981\u8868\u8fbe\u5bf9\u8868\u54e5\u7684\u597d\u611f\uff0c\u54ea\u6015\u8fd9\u610f\u5473\u7740\u53d7\u4f24\uff1b\u58f0\u671b\u5353\u8457\u7684\u7956\u7236\u5728\u6d74\u5ba4\u4e2d\u5bf9\u7537\u5993\u8ffd\u9010\u7231\u6155\uff0c\u6068\u4e0d\u5f97\u8865\u56de\u5931\u53bb\u7684\u65f6\u5149\uff1b\u4e00\u5bf9\u7ae5\u5e74\u597d\u53cb\u4e45\u522b\u91cd\u9022\uff0c\u60c5\u4e0d\u81ea\u7981\u7684\u7231\u4e0a\u540e\u5374\u5bb3\u6015\u66dd\u5149\uff1b\u4e00\u4efd\u5b89\u7a33\u7684\u611f\u60c5\u5173\u7cfb\u5f00\u59cb\u9762\u5bf9\u4e03\u5e74\u4e4b\u75d2\uff0c\u54ea\u6015\u4ed6\u4eec\u4f9d\u7136\u6df1\u7231\u5bf9\u65b9...... \u5f53\u5b83\u4eec\u4ea4\u7ec7\u5728\u4e00\u8d77\uff0c\u5c31\u662f\u201c\u56db\u4e2a\u6708\u4eae\u201d\u3002", "director": ["Sergio Tovar Velarde"], "type": ["\u5267\u60c5", "\u540c\u6027"]}
