{"name": "\u6c38\u8fdc\u4e0d\u518d", "url": "https://movie.douban.com/subject/3313399", "writer": ["Gwen Bagni", "Irwin Gielgud", "Stirling Silliphant", "Adela Rogers St. Johns"], "actor": ["\u963f\u5c14\u5f17\u96f7\u5fb7\u00b7\u5e0c\u533a\u67ef\u514b", "Phyllis Thaxter", "\u8def\u6613\u4e1d\u00b7\u5965\u5c14\u5e03\u91cc\u987f"], "summary": "Karen wakes up in an unfamiliar bed, with a hangover that's even worse than usual. She knows that by getting drunk again she has once more broken her promise to her boyfriend Jeff. Then she realizes that her hand is bandaged and badly injured, and she struggles to remember what happened the night before. She had gone to a party with Jeff, but she felt uncomfortable and lonely, ...", "director": ["Robert Stevens"], "type": ["\u5267\u60c5", "\u60ac\u7591", "\u72af\u7f6a"]}
