{"name": "\u7537\u4eba\u5f97\u6709\u5fc3\u5440", "url": "https://movie.douban.com/subject/1753290", "writer": ["Gal Uchovsky"], "actor": ["Tzak Berkman", "Uri Omanuti", "Sami Huri"], "summary": "Young love blossoms amid the inhabitants of a small town in Israel in this gay fantasy. Guri want to relocate to Tel Aviv before he's &quot;outed&quot;. Nohav want to win a local song contest and who can tell what stud Merito wants?", "director": ["\u4f0a\u85e4\u00b7\u798f\u514b\u65af"], "type": ["\u7231\u60c5", "\u77ed\u7247", "\u6b4c\u821e"]}
