{"name": "\u761f\u75ab\u964d\u4e34", "url": "https://movie.douban.com/subject/1949698", "writer": ["\u7f57\u4f0a\u00b7\u5b89\u5fb7\u68ee"], "actor": ["Klas-G\u00f6sta Olsson", "Anne Tubin", "Lennart Bj\u00f6rklund"], "summary": "This is a very interesting movie with great visuals just like all Roy Andersson movies and it holds a strange somewhat hidden agenda/message. This movie carries a very controversial message about the origin of AIDS which is most likely the reason why the the Swedish Board of Health and Welfare terminated the project. It seams that Roy Andersson doesn't believe in the the theory...", "director": ["\u7f57\u4f0a\u00b7\u5b89\u5fb7\u68ee"], "type": ["\u77ed\u7247"]}
