{"name": "\u6c38\u4e0d\u5c48\u670d", "url": "https://movie.douban.com/subject/25804293", "writer": ["\u6234\u7ef4\u00b7\u9ed1\u5c14"], "actor": ["\u6bd4\u5c14\u00b7\u5948\u4f0a", "\u6d77\u4f26\u5a1c\u00b7\u4f2f\u7ff0\u00b7\u5361\u7279", "\u62c9\u5c14\u592b\u00b7\u8d39\u56e0\u65af"], "summary": "The Johnny Worricker Spy trilogy concludes with Salting the Battlefield, in which our hero with his ex girlfriend, Margot are criss-crossing Europe trying to stay one step ahead of the security services and a vengeful Prime Minister. Worricker is being watched - His family and friends are being watched - He is running out of cash and he needs to make a move to reach an endgame....", "director": ["\u6234\u7ef4\u00b7\u9ed1\u5c14"], "type": ["\u5267\u60c5", "\u60ac\u7591"]}
