{"name": "\u79c1\u7656", "url": "https://movie.douban.com/subject/26309092", "writer": [], "actor": ["Andrew", "Ce", "David", "Ed", "Ido", "Jorge", "Rafael", "Raoni", "Rowland", "Rubi", "Scott", "Simon"], "summary": "Underwear, leather, rubber, jeans, socks, boots, big penises, tattoos, hairy, extended ejaculations, ropes, childhood memories and more. SOLOS portraits a diversity of characters expressing themselves sexually. They speak about their fetishes, connection and fantasies.", "director": ["\u5b89\u4e1c\u5c3c\u5965\u00b7\u8fbe\u00b7\u5e2d\u5c14\u74e6"], "type": ["\u77ed\u7247"]}
